pdftextsplitter/__init__.py
pdftextsplitter/Tests/__init__.py
pdftextsplitter/Tests/Tools/AlineasPresent.py
pdftextsplitter/Tests/Tools/ByteComparison.py
pdftextsplitter/Tests/Tools/CodeCoverage.py
pdftextsplitter/Tests/Tools/CompareImages.py
pdftextsplitter/Tests/Tools/CompareTexts.py
pdftextsplitter/Tests/Tools/DjangoCoverage.py
pdftextsplitter/Tests/Tools/FileComparison.py
pdftextsplitter/Tests/Tools/ImgRMS.py
pdftextsplitter/Tests/Tools/Platformdetection.py
pdftextsplitter/Tests/Tools/ReplaceTextInFile.py
pdftextsplitter/Tests/Tools/TOCElementsPresent.py
pdftextsplitter/Tests/Tools/__init__.py
pdftextsplitter/TextPart/CurrentLine.py
pdftextsplitter/TextPart/Languagemodels.py
pdftextsplitter/TextPart/OpenAI_Keys.py
pdftextsplitter/TextPart/__init__.py
pdftextsplitter/TextPart/body.py
pdftextsplitter/TextPart/breakdown.py
pdftextsplitter/TextPart/calculate_footerboundaries.py
pdftextsplitter/TextPart/calculatefulltree.py
pdftextsplitter/TextPart/calculatetree.py
pdftextsplitter/TextPart/document_metadata.py
pdftextsplitter/TextPart/enum_type.py
pdftextsplitter/TextPart/enumeration.py
pdftextsplitter/TextPart/export.py
pdftextsplitter/TextPart/exportalineas.py
pdftextsplitter/TextPart/exportdecisions.py
pdftextsplitter/TextPart/fill_from_other_textpart.py
pdftextsplitter/TextPart/fontregion.py
pdftextsplitter/TextPart/fontsizehist.py
pdftextsplitter/TextPart/footer.py
pdftextsplitter/TextPart/headlines.py
pdftextsplitter/TextPart/layered_summary.py
pdftextsplitter/TextPart/lineregion.py
pdftextsplitter/TextPart/load.py
pdftextsplitter/TextPart/masterrule.py
pdftextsplitter/TextPart/passinfo.py
pdftextsplitter/TextPart/printcode.py
pdftextsplitter/TextPart/raisedependencies.py
pdftextsplitter/TextPart/read_native_toc.py
pdftextsplitter/TextPart/regex_expressions.py
pdftextsplitter/TextPart/shiftcontents.py
pdftextsplitter/TextPart/stringmatch.py
pdftextsplitter/TextPart/summarize.py
pdftextsplitter/TextPart/summarize_openai.py
pdftextsplitter-2.1.4.dist-info/LICENSE.txt
pdftextsplitter-2.1.4.dist-info/METADATA
pdftextsplitter-2.1.4.dist-info/WHEEL
pdftextsplitter-2.1.4.dist-info/top_level.txt
pdftextsplitter-2.1.4.dist-info/RECORD
