Metadata-Version: 2.1
Name: pdftextsplitter
Version: 2.1.4
Summary: This packages can read PDF documents and automatically recognise chapter-titles, enumerations and other elements in the text and summarize the document part-by-part
Home-page: https://gitlab.com/datainnovatielab/public/pdftextsplitter/dist/
Download-URL: https://gitlab.com/datainnovatielab/public/pdftextsplitter/dist/
Author: Unit Data en Innovatie, Ministerie van Infrastructuur en Waterstaat, Netherlands
Author-email: dataloket@minienw.nl
License: MIT
Keywords: NLP,PDF,Text recognition,Structure recognition,ChatGPT
Classifier: Development Status :: 3 - Alpha
Classifier: Intended Audience :: Developers
Classifier: Topic :: Software Development :: Build Tools
Classifier: License :: OSI Approved :: MIT License
Classifier: Programming Language :: Python :: 3.10
Requires-Python: >=3.10
License-File: LICENSE.txt
Requires-Dist: setuptools >=59.6.0
Requires-Dist: wheel >=0.41.1
Requires-Dist: build >=0.10.0
Requires-Dist: numpy >=1.25.2
Requires-Dist: pandas >=2.0.3
Requires-Dist: matplotlib >=3.7.2
Requires-Dist: pillow >=10.0.0
Requires-Dist: PyPDF2 >=3.0.1
Requires-Dist: openai >=1.3.0
Requires-Dist: tiktoken >=0.4.0
Requires-Dist: pymupdf <=1.22.5,>=1.22.2
Requires-Dist: pdfminer.six >=20221105
Requires-Dist: thefuzz >=0.19.0
Requires-Dist: transformers >=4.36.2
Requires-Dist: nltk >=3.8.1
Requires-Dist: pytest <=7.4.0,>=7.3.0
Requires-Dist: coverage >=7.3.0
Requires-Dist: pylint >=2.17.5
